selinux/__init__.py
selinux-0.2.0.dist-info/LICENSE
selinux-0.2.0.dist-info/METADATA
selinux-0.2.0.dist-info/WHEEL
selinux-0.2.0.dist-info/top_level.txt
selinux-0.2.0.dist-info/zip-safe
selinux-0.2.0.dist-info/RECORD
