Metadata-Version: 2.1
Name: selinux
Version: 0.2.0
Summary: shim selinux module
Home-page: https://github.com/pycontribs/selinux
Author: Sorin Sbarnea
Author-email: sorin.sbarnea@gmail.com
Maintainer: Sorin Sbarnea
Maintainer-email: sorin.sbarnea@gmail.com
License: MIT license
Project-URL: Bug Tracker, https://github.com/pycontribs/selinux/issues
Project-URL: Release Management, https://github.com/pycontribs/selinux/projects
Project-URL: CI: Travis, https://travis-ci.com/pycontribs/selinux
Project-URL: Source Code, https://github.com/pycontribs/selinux
Keywords: selinux,virtualenv
Platform: UNKNOWN
Classifier: Development Status :: 5 - Production/Stable
Classifier: Environment :: Console
Classifier: Intended Audience :: Developers
Classifier: Intended Audience :: Information Technology
Classifier: Intended Audience :: System Administrators
Classifier: License :: OSI Approved :: MIT License
Classifier: Natural Language :: English
Classifier: Operating System :: OS Independent
Classifier: Programming Language :: Python :: 2
Classifier: Programming Language :: Python :: 2.7
Classifier: Programming Language :: Python :: 3
Classifier: Programming Language :: Python :: 3.5
Classifier: Programming Language :: Python :: 3.6
Classifier: Programming Language :: Python :: 3.7
Classifier: Topic :: System :: Systems Administration
Classifier: Topic :: Utilities
Requires-Python: !=3.0.*,!=3.1.*,!=3.2.*,!=3.3.*,>=2.7
